{
  "type": "Feature",
  "properties": {
    "gn:admin1_code":"9.0",
    "gn:asciiname":"Neugrutt",
    "gn:country_code":"LI",
    "gn:dem":479,
    "gn:feature_class":"P",
    "gn:feature_code":"PPL",
    "gn:name":"Neugr\u00fctt",
    "gn:population":0,
    "gn:timezone":"Europe/Vaduz",
    "iso:country":"LI",
    "name:deu_x_preferred":[
        "Neugr\u00fctt"
    ],
    "wof:name":"Neugrutt",
    "wof:placetype":"locality"
},
  "geometry": {"coordinates":[9.52337,47.08782],"type":"Point"}
}