{
  "type": "Feature",
  "properties": {
    "gn:admin1_code":"1.0",
    "gn:asciiname":"Mals",
    "gn:country_code":"LI",
    "gn:dem":477,
    "gn:feature_class":"P",
    "gn:feature_code":"PPL",
    "gn:name":"M\u00e4ls",
    "gn:population":0,
    "gn:timezone":"Europe/Vaduz",
    "iso:country":"LI",
    "name:und_x_variant":[
        "M\u00e4ls"
    ],
    "wof:name":"Mals",
    "wof:placetype":"locality"
},
  "geometry": {"coordinates":[9.49568,47.06105],"type":"Point"}
}