{
  "type": "Feature",
  "properties": {
    "gn:admin1_code":"1.0",
    "gn:asciiname":"Mals",
    "gn:country_code":"LI",
    "gn:dem":477,
    "gn:feature_class":"P",
    "gn:feature_code":"PPL",
    "gn:name":"M\u00e4ls",
    "gn:population":0,
    "gn:timezone":"Europe/Vaduz",
    "iso:country":"LI",
    "name:arg_x_preferred":[
        "M\u00e4ls"
    ],
    "name:ell_x_preferred":[
        "\u039c\u03b5\u03bb\u03c2"
    ],
    "name:fas_x_preferred":[
        "\u0645\u0644\u0633"
    ],
    "name:hye_x_preferred":[
        "\u0544\u0565\u056c\u057d"
    ],
    "name:lmo_x_preferred":[
        "M\u00e4ls"
    ],
    "name:mkd_x_preferred":[
        "\u041c\u0435\u043b\u0441"
    ],
    "name:pol_x_preferred":[
        "M\u00e4ls"
    ],
    "name:rus_x_preferred":[
        "\u041c\u0435\u043b\u044c\u0441"
    ],
    "name:spa_x_preferred":[
        "M\u00e4ls"
    ],
    "name:ukr_x_preferred":[
        "\u041c\u0435\u043b\u044c\u0441"
    ],
    "name:und_x_variant":[
        "M\u00e4ls"
    ],
    "name:urd_x_preferred":[
        "\u0645\u0627\u0644\u0633"
    ],
    "name:vie_x_preferred":[
        "M\u00e4ls"
    ],
    "wof:name":"Mals",
    "wof:placetype":"locality"
},
  "geometry": {"coordinates":[9.49568,47.06105],"type":"Point"}
}