{
  "type": "Feature",
  "properties": {
    "gn:gn_country":"LI",
    "gn:gn_fcode":"PPL",
    "gn:gn_pop":0,
    "iso:country":"LI",
    "name:arg_x_preferred":[
        "Bendern"
    ],
    "name:bel_x_preferred":[
        "\u0411\u0435\u043d\u0434\u044d\u0440\u043d"
    ],
    "name:bul_x_preferred":[
        "\u0411\u0435\u043d\u0434\u0435\u0440\u043d"
    ],
    "name:ceb_x_preferred":[
        "Bendern"
    ],
    "name:deu_x_preferred":[
        "Bendern"
    ],
    "name:ell_x_preferred":[
        "\u039c\u03c0\u03ad\u03bd\u03c4\u03b5\u03c1\u03bd"
    ],
    "name:eng_x_preferred":[
        "Bendern"
    ],
    "name:fas_x_preferred":[
        "\u0628\u0646\u062f\u0631\u0646"
    ],
    "name:fra_x_preferred":[
        "Bendern"
    ],
    "name:gsw_x_preferred":[
        "Bendra"
    ],
    "name:hye_x_preferred":[
        "\u0532\u0565\u0576\u0564\u0565\u0580\u0576"
    ],
    "name:lmo_x_preferred":[
        "Bendern"
    ],
    "name:mkd_x_preferred":[
        "\u0411\u0435\u043d\u0434\u0435\u0440\u043d"
    ],
    "name:nld_x_preferred":[
        "Bendern"
    ],
    "name:pol_x_preferred":[
        "Bendern"
    ],
    "name:rus_x_preferred":[
        "\u0411\u0435\u043d\u0434\u0435\u0440\u043d"
    ],
    "name:spa_x_preferred":[
        "Bendern"
    ],
    "name:swe_x_preferred":[
        "Bendern"
    ],
    "name:ukr_x_preferred":[
        "\u0411\u0435\u043d\u0434\u0435\u0440\u043d"
    ],
    "name:zho_x_preferred":[
        "\u99ac\u723e\u90a6"
    ],
    "qs_pg:aaroncc":"LI",
    "qs_pg:gn_country":"LI",
    "qs_pg:gn_fcode":"PPL",
    "qs_pg:gn_pop":0,
    "qs_pg:name":"Bendern",
    "qs_pg:name_adm0":"Liechtenstein",
    "qs_pg:name_adm1":"Gamprin",
    "qs_pg:photos":52,
    "qs_pg:photos_1k":11,
    "qs_pg:photos_9k":1,
    "qs_pg:photos_9r":2,
    "qs_pg:photos_all":52,
    "qs_pg:photos_sr":2,
    "qs_pg:pop_sr":0,
    "qs_pg:qs_pg_placetype":"locality",
    "qs_pg:qs_pg_placetype_gp":"Town",
    "qs_pg:woe_adm0":23424879,
    "woe:adm0_id":23424879,
    "woe:name_adm0":"Liechtenstein",
    "woe:name_adm1":"Gamprin",
    "woe:placetype":"Town",
    "wof:name":"Bendern",
    "wof:placetype":"locality"
},
  "geometry": {"coordinates":[9.50678,47.21199],"type":"Point"}
}