{
  "type": "Feature",
  "properties": {
    "gn:admin1_code":"10.0",
    "gn:asciiname":"Eggalti",
    "gn:country_code":"LI",
    "gn:dem":1027,
    "gn:feature_class":"P",
    "gn:feature_code":"PPL",
    "gn:name":"Eggalti",
    "gn:population":0,
    "gn:timezone":"Europe/Vaduz",
    "iso:country":"LI",
    "wof:name":"Eggalti",
    "wof:placetype":"locality"
},
  "geometry": {"coordinates":[9.54349,47.12464],"type":"Point"}
}