{
  "type": "Feature",
  "properties": {
    "gn:admin1_code":"11.0",
    "gn:asciiname":"Bi den undera Hotta",
    "gn:country_code":"LI",
    "gn:dem":1502,
    "gn:feature_class":"P",
    "gn:feature_code":"PPLL",
    "gn:name":"Bi den undera H\u00f6tta",
    "gn:population":0,
    "gn:timezone":"Europe/Vaduz",
    "iso:country":"LI",
    "wof:name":"Bi den undera Hotta",
    "wof:placetype":"locality"
},
  "geometry": {"coordinates":[9.59886,47.10769000000001],"type":"Point"}
}