{
  "type": "Feature",
  "properties": {
    "gn:admin1_code":"10.0",
    "gn:asciiname":"Ruti",
    "gn:country_code":"LI",
    "gn:dem":841,
    "gn:feature_class":"P",
    "gn:feature_code":"PPL",
    "gn:name":"R\u00fcti",
    "gn:population":0,
    "gn:timezone":"Europe/Vaduz",
    "iso:country":"LI",
    "name:ceb_x_preferred":[
        "Ruti"
    ],
    "name:deu_x_preferred":[
        "R\u00fcti"
    ],
    "wof:name":"Ruti",
    "wof:placetype":"locality"
},
  "geometry": {"coordinates":[9.54498,47.10799],"type":"Point"}
}