{
  "type": "Feature",
  "properties": {
    "gn:admin1_code":"7.0",
    "gn:asciiname":"Bim Stall",
    "gn:country_code":"LI",
    "gn:dem":1405,
    "gn:feature_class":"P",
    "gn:feature_code":"PPL",
    "gn:name":"Bim Stall",
    "gn:population":0,
    "gn:timezone":"Europe/Vaduz",
    "iso:country":"LI",
    "wof:name":"Bim Stall",
    "wof:placetype":"locality"
},
  "geometry": {"coordinates":[9.60064,47.13981],"type":"Point"}
}