{
  "type": "Feature",
  "properties": {
    "gn:admin1_code":"10.0",
    "gn:asciiname":"Bunda",
    "gn:country_code":"LI",
    "gn:dem":1242,
    "gn:feature_class":"P",
    "gn:feature_code":"PPLL",
    "gn:name":"B\u00fcnda",
    "gn:population":0,
    "gn:timezone":"Europe/Vaduz",
    "iso:country":"LI",
    "name:ceb_x_preferred":[
        "Bunda"
    ],
    "name:deu_x_preferred":[
        "Bunda"
    ],
    "name:fra_x_preferred":[
        "Bunda"
    ],
    "name:ita_x_preferred":[
        "Bunda"
    ],
    "name:por_x_preferred":[
        "Bunda"
    ],
    "name:swe_x_preferred":[
        "Bunda"
    ],
    "wof:name":"Bunda",
    "wof:placetype":"locality"
},
  "geometry": {"coordinates":[9.55543,47.12374000000001],"type":"Point"}
}