{
  "type": "Feature",
  "properties": {
    "gn:admin1_code":"10.0",
    "gn:asciiname":"Mitatsch",
    "gn:country_code":"LI",
    "gn:dem":1268,
    "gn:feature_class":"P",
    "gn:feature_code":"PPL",
    "gn:name":"Mit\u00e4tsch",
    "gn:population":0,
    "gn:timezone":"Europe/Vaduz",
    "iso:country":"LI",
    "wof:name":"Mitatsch",
    "wof:placetype":"locality"
},
  "geometry": {"coordinates":[9.55327,47.12501],"type":"Point"}
}